acore_server/__init__.py
acore_server/_version.py
acore_server/api.py
acore_server/constants.py
acore_server/exc.py
acore_server/fleet.py
acore_server/logger.py
acore_server/manager.py
acore_server/paths.py
acore_server/server.py
acore_server/server_helper_mixin.py
acore_server/server_operation_mixin.py
acore_server/server_workflow_mixin.py
acore_server/utils.py
acore_server/wserver_infra_exports.py
acore_server/docs/__init__.py
acore_server/tests/__init__.py
acore_server/tests/helper.py
acore_server/vendor/__init__.py
acore_server/vendor/hashes.py
acore_server/vendor/pytest_cov_helper.py
acore_server-1.1.4.dist-info/AUTHORS.rst
acore_server-1.1.4.dist-info/LICENSE.txt
acore_server-1.1.4.dist-info/METADATA
acore_server-1.1.4.dist-info/WHEEL
acore_server-1.1.4.dist-info/top_level.txt
acore_server-1.1.4.dist-info/RECORD
